{
  "endpoint": "https://api.pokemontcg.io/v2/cards",
  "params": {
    "q": "name:quaxly"
  },
  "cache_key": "a5ce8f8c24eab0ac90ab67825ba83dc6",
  "cached_at": 1765916230.558239,
  "response": {
    "data": [
      {
        "id": "sv1-52",
        "name": "Quaxly",
        "supertype": "Pokémon",
        "subtypes": [
          "Basic"
        ],
        "hp": "70",
        "types": [
          "Water"
        ],
        "attacks": [
          {
            "cost": [
              "Colorless"
            ],
            "name": "Pound",
            "damage": "10",
            "text": "",
            "convertedEnergyCost": 1
          },
          {
            "cost": [
              "Water",
              "Colorless"
            ],
            "name": "Kick",
            "damage": "20",
            "text": "",
            "convertedEnergyCost": 2
          }
        ],
        "weaknesses": [
          {
            "type": "Lightning",
            "value": "×2"
          }
        ],
        "retreatCost": [
          "Colorless"
        ],
        "convertedRetreatCost": 1,
        "set": {
          "id": "sv1",
          "name": "Scarlet & Violet",
          "series": "Scarlet & Violet",
          "printedTotal": 198,
          "total": 258,
          "legalities": {
            "unlimited": "Legal",
            "standard": "Legal",
            "expanded": "Legal"
          },
          "releaseDate": "2023/03/31",
          "updatedAt": "2023/03/31 15:45:00",
          "images": {
            "symbol": "https://images.pokemontcg.io/sv1/symbol.png",
            "logo": "https://images.pokemontcg.io/sv1/logo.png"
          }
        },
        "number": "52",
        "artist": "Mizue",
        "rarity": "Common",
        "flavorText": "This Pokémon migrated to Paldea from distant lands long ago. The gel secreted by its feathers repels water and grime.",
        "nationalPokedexNumbers": [
          912
        ],
        "legalities": {
          "unlimited": "Legal",
          "standard": "Legal",
          "expanded": "Legal"
        },
        "regulationMark": "G",
        "images": {
          "small": "https://images.pokemontcg.io/sv1/52.png",
          "large": "https://images.pokemontcg.io/sv1/52_hires.png"
        },
        "tcgplayer": {
          "url": "https://prices.pokemontcg.io/tcgplayer/sv1-52",
          "updatedAt": "2025/12/16",
          "prices": {
            "normal": {
              "low": 0.01,
              "mid": 0.1,
              "high": 1.91,
              "market": 0.06,
              "directLow": null
            },
            "reverseHolofoil": {
              "low": 0.08,
              "mid": 0.2,
              "high": 25.0,
              "market": 0.16,
              "directLow": null
            }
          }
        },
        "cardmarket": {
          "url": "https://prices.pokemontcg.io/cardmarket/sv1-52",
          "updatedAt": "2025/12/16",
          "prices": {
            "averageSellPrice": 0.3,
            "lowPrice": 0.02,
            "trendPrice": 0.3,
            "germanProLow": 0.0,
            "suggestedPrice": 0.0,
            "reverseHoloSell": 0.0,
            "reverseHoloLow": 0.0,
            "reverseHoloTrend": 0.0,
            "lowPriceExPlus": 0.02,
            "avg1": 0.5,
            "avg7": 0.21,
            "avg30": 0.31,
            "reverseHoloAvg1": 0.0,
            "reverseHoloAvg7": 0.0,
            "reverseHoloAvg30": 0.0
          }
        }
      },
      {
        "id": "svp-3",
        "name": "Quaxly",
        "supertype": "Pokémon",
        "subtypes": [
          "Basic"
        ],
        "hp": "70",
        "types": [
          "Water"
        ],
        "attacks": [
          {
            "name": "Water Splash",
            "cost": [
              "Water",
              "Colorless"
            ],
            "convertedEnergyCost": 2,
            "damage": "20+",
            "text": "Flip a coin. If heads, this attack does 20 more damage."
          }
        ],
        "weaknesses": [
          {
            "type": "Lightning",
            "value": "×2"
          }
        ],
        "retreatCost": [
          "Colorless"
        ],
        "convertedRetreatCost": 1,
        "set": {
          "id": "svp",
          "name": "Scarlet & Violet Black Star Promos",
          "series": "Scarlet & Violet",
          "printedTotal": 215,
          "total": 196,
          "legalities": {
            "unlimited": "Legal",
            "standard": "Legal",
            "expanded": "Legal"
          },
          "ptcgoCode": "PR-SV",
          "releaseDate": "2023/01/01",
          "updatedAt": "2024/11/09 13:20:00",
          "images": {
            "symbol": "https://images.pokemontcg.io/svp/symbol.png",
            "logo": "https://images.pokemontcg.io/svp/logo.png"
          }
        },
        "number": "3",
        "artist": "Narumi Sato",
        "rarity": "Promo",
        "flavorText": "This Pokémon migrated to Paldea from distant lands long ago. The gel secreted by its feathers repels water and grime.",
        "nationalPokedexNumbers": [
          912
        ],
        "legalities": {
          "unlimited": "Legal",
          "standard": "Legal",
          "expanded": "Legal"
        },
        "regulationMark": "G",
        "images": {
          "small": "https://images.pokemontcg.io/svp/3.png",
          "large": "https://images.pokemontcg.io/svp/3_hires.png"
        },
        "tcgplayer": {
          "url": "https://prices.pokemontcg.io/tcgplayer/svp-3",
          "updatedAt": "2025/12/16",
          "prices": {
            "holofoil": {
              "low": 1.0,
              "mid": 2.0,
              "high": 15.93,
              "market": 2.0,
              "directLow": 15.93
            }
          }
        },
        "cardmarket": {
          "url": "https://prices.pokemontcg.io/cardmarket/svp-3",
          "updatedAt": "2025/12/16",
          "prices": {
            "averageSellPrice": 2.25,
            "lowPrice": 0.79,
            "trendPrice": 2.37,
            "germanProLow": 0.0,
            "suggestedPrice": 0.0,
            "reverseHoloSell": 0.0,
            "reverseHoloLow": 0.0,
            "reverseHoloTrend": 0.0,
            "lowPriceExPlus": 1.0,
            "avg1": 2.99,
            "avg7": 2.57,
            "avg30": 2.33,
            "reverseHoloAvg1": 0.0,
            "reverseHoloAvg7": 0.0,
            "reverseHoloAvg30": 0.0
          }
        }
      },
      {
        "id": "sv2-50",
        "name": "Quaxly",
        "supertype": "Pokémon",
        "subtypes": [
          "Basic"
        ],
        "hp": "70",
        "types": [
          "Water"
        ],
        "attacks": [
          {
            "cost": [
              "Water"
            ],
            "name": "Reckless Charge",
            "damage": "30",
            "text": "This Pokémon also does 10 damage to itself.",
            "convertedEnergyCost": 1
          }
        ],
        "weaknesses": [
          {
            "type": "Lightning",
            "value": "×2"
          }
        ],
        "retreatCost": [
          "Colorless"
        ],
        "convertedRetreatCost": 1,
        "set": {
          "id": "sv2",
          "name": "Paldea Evolved",
          "series": "Scarlet & Violet",
          "printedTotal": 193,
          "total": 279,
          "legalities": {
            "unlimited": "Legal",
            "standard": "Legal",
            "expanded": "Legal"
          },
          "releaseDate": "2023/06/09",
          "updatedAt": "2023/06/09 15:00:00",
          "images": {
            "symbol": "https://images.pokemontcg.io/sv2/symbol.png",
            "logo": "https://images.pokemontcg.io/sv2/logo.png"
          }
        },
        "number": "50",
        "artist": "Naoki Saito",
        "rarity": "Common",
        "flavorText": "This Pokémon migrated to Paldea from distant lands long ago. The gel secreted by its feathers repels water and grime.",
        "nationalPokedexNumbers": [
          912
        ],
        "legalities": {
          "unlimited": "Legal",
          "standard": "Legal",
          "expanded": "Legal"
        },
        "regulationMark": "G",
        "images": {
          "small": "https://images.pokemontcg.io/sv2/50.png",
          "large": "https://images.pokemontcg.io/sv2/50_hires.png"
        },
        "tcgplayer": {
          "url": "https://prices.pokemontcg.io/tcgplayer/sv2-50",
          "updatedAt": "2025/12/16",
          "prices": {
            "reverseHolofoil": {
              "low": 0.01,
              "mid": 0.15,
              "high": 2.0,
              "market": 0.07,
              "directLow": null
            },
            "normal": {
              "low": 0.01,
              "mid": 0.1,
              "high": 1.53,
              "market": 0.05,
              "directLow": null
            }
          }
        },
        "cardmarket": {
          "url": "https://prices.pokemontcg.io/cardmarket/sv2-50",
          "updatedAt": "2025/12/16",
          "prices": {
            "averageSellPrice": 0.04,
            "lowPrice": 0.02,
            "trendPrice": 0.04,
            "germanProLow": 0.0,
            "suggestedPrice": 0.0,
            "reverseHoloSell": 0.1,
            "reverseHoloLow": 0.02,
            "reverseHoloTrend": 0.09,
            "lowPriceExPlus": 0.02,
            "avg1": 0.04,
            "avg7": 0.04,
            "avg30": 0.04,
            "reverseHoloAvg1": 0.09,
            "reverseHoloAvg7": 0.09,
            "reverseHoloAvg30": 0.09
          }
        }
      },
      {
        "id": "sv2-49",
        "name": "Quaxly",
        "supertype": "Pokémon",
        "subtypes": [
          "Basic"
        ],
        "hp": "60",
        "types": [
          "Water"
        ],
        "attacks": [
          {
            "cost": [
              "Water",
              "Colorless"
            ],
            "name": "Apply Gel",
            "damage": "20",
            "text": "During your opponent's next turn, if the Defending Pokémon tries to attack, your opponent flips a coin. If tails, that attack doesn't happen.",
            "convertedEnergyCost": 2
          }
        ],
        "weaknesses": [
          {
            "type": "Lightning",
            "value": "×2"
          }
        ],
        "retreatCost": [
          "Colorless"
        ],
        "convertedRetreatCost": 1,
        "set": {
          "id": "sv2",
          "name": "Paldea Evolved",
          "series": "Scarlet & Violet",
          "printedTotal": 193,
          "total": 279,
          "legalities": {
            "unlimited": "Legal",
            "standard": "Legal",
            "expanded": "Legal"
          },
          "releaseDate": "2023/06/09",
          "updatedAt": "2023/06/09 15:00:00",
          "images": {
            "symbol": "https://images.pokemontcg.io/sv2/symbol.png",
            "logo": "https://images.pokemontcg.io/sv2/logo.png"
          }
        },
        "number": "49",
        "artist": "sui",
        "rarity": "Common",
        "flavorText": "This Pokémon migrated to Paldea from distant lands long ago. The gel secreted by its feathers repels water and grime.",
        "nationalPokedexNumbers": [
          912
        ],
        "legalities": {
          "unlimited": "Legal",
          "standard": "Legal",
          "expanded": "Legal"
        },
        "regulationMark": "G",
        "images": {
          "small": "https://images.pokemontcg.io/sv2/49.png",
          "large": "https://images.pokemontcg.io/sv2/49_hires.png"
        },
        "tcgplayer": {
          "url": "https://prices.pokemontcg.io/tcgplayer/sv2-49",
          "updatedAt": "2025/12/16",
          "prices": {
            "normal": {
              "low": 0.01,
              "mid": 0.1,
              "high": 20.0,
              "market": 0.06,
              "directLow": null
            },
            "reverseHolofoil": {
              "low": 0.01,
              "mid": 0.17,
              "high": 1.49,
              "market": 0.15,
              "directLow": null
            }
          }
        },
        "cardmarket": {
          "url": "https://prices.pokemontcg.io/cardmarket/sv2-49",
          "updatedAt": "2025/12/16",
          "prices": {
            "averageSellPrice": 0.04,
            "lowPrice": 0.02,
            "trendPrice": 0.04,
            "germanProLow": 0.0,
            "suggestedPrice": 0.0,
            "reverseHoloSell": 0.13,
            "reverseHoloLow": 0.02,
            "reverseHoloTrend": 0.18,
            "lowPriceExPlus": 0.02,
            "avg1": 0.04,
            "avg7": 0.04,
            "avg30": 0.04,
            "reverseHoloAvg1": 0.3,
            "reverseHoloAvg7": 0.12,
            "reverseHoloAvg30": 0.14
          }
        }
      },
      {
        "id": "sv2-206",
        "name": "Quaxly",
        "supertype": "Pokémon",
        "subtypes": [
          "Basic"
        ],
        "hp": "60",
        "types": [
          "Water"
        ],
        "attacks": [
          {
            "cost": [
              "Water",
              "Colorless"
            ],
            "name": "Apply Gel",
            "damage": "20",
            "text": "During your opponent's next turn, if the Defending Pokémon tries to attack, your opponent flips a coin. If tails, that attack doesn't happen.",
            "convertedEnergyCost": 2
          }
        ],
        "weaknesses": [
          {
            "type": "Lightning",
            "value": "×2"
          }
        ],
        "retreatCost": [
          "Colorless"
        ],
        "convertedRetreatCost": 1,
        "set": {
          "id": "sv2",
          "name": "Paldea Evolved",
          "series": "Scarlet & Violet",
          "printedTotal": 193,
          "total": 279,
          "legalities": {
            "unlimited": "Legal",
            "standard": "Legal",
            "expanded": "Legal"
          },
          "releaseDate": "2023/06/09",
          "updatedAt": "2023/06/09 15:00:00",
          "images": {
            "symbol": "https://images.pokemontcg.io/sv2/symbol.png",
            "logo": "https://images.pokemontcg.io/sv2/logo.png"
          }
        },
        "number": "206",
        "artist": "Souichirou Gunjima",
        "rarity": "Illustration Rare",
        "flavorText": "This Pokémon migrated to Paldea from distant lands long ago. The gel secreted by its feathers repels water and grime.",
        "nationalPokedexNumbers": [
          912
        ],
        "legalities": {
          "unlimited": "Legal",
          "standard": "Legal",
          "expanded": "Legal"
        },
        "regulationMark": "G",
        "images": {
          "small": "https://images.pokemontcg.io/sv2/206.png",
          "large": "https://images.pokemontcg.io/sv2/206_hires.png"
        },
        "tcgplayer": {
          "url": "https://prices.pokemontcg.io/tcgplayer/sv2-206",
          "updatedAt": "2025/12/16",
          "prices": {
            "holofoil": {
              "low": 8.5,
              "mid": 11.48,
              "high": 30.0,
              "market": 11.57,
              "directLow": 14.99
            }
          }
        },
        "cardmarket": {
          "url": "https://prices.pokemontcg.io/cardmarket/sv2-206",
          "updatedAt": "2025/11/18",
          "prices": {
            "averageSellPrice": 7.27,
            "lowPrice": 3.99,
            "trendPrice": 6.9,
            "germanProLow": 0.0,
            "suggestedPrice": 0.0,
            "reverseHoloSell": 0.0,
            "reverseHoloLow": 0.0,
            "reverseHoloTrend": 0.0,
            "lowPriceExPlus": 3.99,
            "avg1": 6.79,
            "avg7": 6.69,
            "avg30": 7.15,
            "reverseHoloAvg1": 0.0,
            "reverseHoloAvg7": 0.0,
            "reverseHoloAvg30": 0.0
          }
        }
      },
      {
        "id": "svp-82",
        "name": "Quaxly",
        "supertype": "Pokémon",
        "subtypes": [
          "Basic"
        ],
        "hp": "70",
        "types": [
          "Water"
        ],
        "attacks": [
          {
            "cost": [
              "Water"
            ],
            "name": "Reckless Charge",
            "damage": "30",
            "text": "This Pokémon also does 10 damage to itself.",
            "convertedEnergyCost": 1
          }
        ],
        "weaknesses": [
          {
            "type": "Lightning",
            "value": "×2"
          }
        ],
        "retreatCost": [
          "Colorless"
        ],
        "convertedRetreatCost": 1,
        "set": {
          "id": "svp",
          "name": "Scarlet & Violet Black Star Promos",
          "series": "Scarlet & Violet",
          "printedTotal": 215,
          "total": 196,
          "legalities": {
            "unlimited": "Legal",
            "standard": "Legal",
            "expanded": "Legal"
          },
          "ptcgoCode": "PR-SV",
          "releaseDate": "2023/01/01",
          "updatedAt": "2024/11/09 13:20:00",
          "images": {
            "symbol": "https://images.pokemontcg.io/svp/symbol.png",
            "logo": "https://images.pokemontcg.io/svp/logo.png"
          }
        },
        "number": "82",
        "artist": "GIDORA",
        "rarity": "Promo",
        "flavorText": "This Pokémon migrated to Paldea from distant lands long ago. The gel secreted by its feathers repels water and grime.",
        "nationalPokedexNumbers": [
          912
        ],
        "legalities": {
          "unlimited": "Legal",
          "standard": "Legal",
          "expanded": "Legal"
        },
        "regulationMark": "G",
        "images": {
          "small": "https://images.pokemontcg.io/svp/82.png",
          "large": "https://images.pokemontcg.io/svp/82_hires.png"
        },
        "tcgplayer": {
          "url": "https://prices.pokemontcg.io/tcgplayer/svp-82",
          "updatedAt": "2025/12/16",
          "prices": {
            "holofoil": {
              "low": 0.82,
              "mid": 1.42,
              "high": 10.0,
              "market": 1.32,
              "directLow": 1.4
            }
          }
        },
        "cardmarket": {
          "url": "https://prices.pokemontcg.io/cardmarket/svp-82",
          "updatedAt": "2025/12/13",
          "prices": {
            "averageSellPrice": 0.73,
            "lowPrice": 0.2,
            "trendPrice": 0.83,
            "germanProLow": 0.0,
            "suggestedPrice": 0.0,
            "reverseHoloSell": 0.0,
            "reverseHoloLow": 0.0,
            "reverseHoloTrend": 0.0,
            "lowPriceExPlus": 0.2,
            "avg1": 0.54,
            "avg7": 0.76,
            "avg30": 0.76,
            "reverseHoloAvg1": 0.0,
            "reverseHoloAvg7": 0.0,
            "reverseHoloAvg30": 0.0
          }
        }
      },
      {
        "id": "sv8-50",
        "name": "Quaxly",
        "supertype": "Pokémon",
        "subtypes": [
          "Basic"
        ],
        "hp": "60",
        "types": [
          "Water"
        ],
        "attacks": [
          {
            "name": "Aerial Ace",
            "cost": [
              "Water"
            ],
            "convertedEnergyCost": 1,
            "damage": "10+",
            "text": "Flip a coin. If heads, this attack does 20 more damage."
          }
        ],
        "weaknesses": [
          {
            "type": "Lightning",
            "value": "×2"
          }
        ],
        "retreatCost": [
          "Colorless"
        ],
        "convertedRetreatCost": 1,
        "set": {
          "id": "sv8",
          "name": "Surging Sparks",
          "series": "Scarlet & Violet",
          "printedTotal": 191,
          "total": 252,
          "legalities": {
            "unlimited": "Legal",
            "standard": "Legal",
            "expanded": "Legal"
          },
          "ptcgoCode": "SSP",
          "releaseDate": "2024/11/08",
          "updatedAt": "2024/11/07 22:00:00",
          "images": {
            "symbol": "https://images.pokemontcg.io/sv8/symbol.png",
            "logo": "https://images.pokemontcg.io/sv8/logo.png"
          }
        },
        "number": "50",
        "rarity": "Common",
        "nationalPokedexNumbers": [
          912
        ],
        "legalities": {
          "unlimited": "Legal",
          "standard": "Legal",
          "expanded": "Legal"
        },
        "regulationMark": "H",
        "images": {
          "small": "https://images.pokemontcg.io/sv8/50.png",
          "large": "https://images.pokemontcg.io/sv8/50_hires.png"
        },
        "tcgplayer": {
          "url": "https://prices.pokemontcg.io/tcgplayer/sv8-50",
          "updatedAt": "2025/12/16",
          "prices": {
            "normal": {
              "low": 0.01,
              "mid": 0.1,
              "high": 1.53,
              "market": 0.03,
              "directLow": 0.03
            },
            "reverseHolofoil": {
              "low": 0.01,
              "mid": 0.15,
              "high": 40.0,
              "market": 0.12,
              "directLow": 0.06
            }
          }
        },
        "cardmarket": {
          "url": "https://prices.pokemontcg.io/cardmarket/sv8-50",
          "updatedAt": "2025/12/16",
          "prices": {
            "averageSellPrice": 0.03,
            "lowPrice": 0.02,
            "trendPrice": 0.02,
            "germanProLow": 0.0,
            "suggestedPrice": 0.0,
            "reverseHoloSell": 0.08,
            "reverseHoloLow": 0.02,
            "reverseHoloTrend": 0.09,
            "lowPriceExPlus": 0.02,
            "avg1": 0.03,
            "avg7": 0.03,
            "avg30": 0.03,
            "reverseHoloAvg1": 0.05,
            "reverseHoloAvg7": 0.07,
            "reverseHoloAvg30": 0.08
          }
        }
      }
    ],
    "page": 1,
    "pageSize": 250,
    "count": 7,
    "totalCount": 7
  }
}